thoth/lab/__init__.py
thoth/lab/adviser.py
thoth/lab/common.py
thoth/lab/convert.py
thoth/lab/dependency_monkey.py
thoth/lab/exception.py
thoth/lab/graph.py
thoth/lab/inspection.py
thoth/lab/inspection_report.py
thoth/lab/security.py
thoth/lab/solver.py
thoth/lab/underscore.py
thoth/lab/utils.py
thoth/lab/viz/__init__.py
thoth/lab/viz/assets/css/d3.css
thoth/lab/viz/assets/js/dynamic/diagonal.js
thoth/lab/viz/assets/js/static/diagonal.js
thoth_lab-0.2.6.dist-info/DESCRIPTION.rst
thoth_lab-0.2.6.dist-info/METADATA
thoth_lab-0.2.6.dist-info/RECORD
thoth_lab-0.2.6.dist-info/WHEEL
thoth_lab-0.2.6.dist-info/metadata.json
thoth_lab-0.2.6.dist-info/top_level.txt
