Metadata-Version: 2.0
Name: thoth-lab
Version: 0.2.6
Summary: Code for Thoth experiments in Jupyter notebooks.
Home-page: UNKNOWN
Author: Fridolin Pokorny
Author-email: fridolin@redhat.com
License: GPLv3+
Platform: UNKNOWN
Requires-Dist: thoth-storages
Requires-Dist: thoth-python
Requires-Dist: ipython
Requires-Dist: ipykernel
Requires-Dist: requests
Requires-Dist: networkx
Requires-Dist: pandas
Requires-Dist: pandas-profiling
Requires-Dist: prettyprinter
Requires-Dist: plotly
Requires-Dist: cufflinks
Requires-Dist: matplotlib
Requires-Dist: jupyter-require
Requires-Dist: jupyter-contrib-nbextensions
Requires-Dist: scikit-learn
Requires-Dist: autopep8
